bot_controller/__init__.py
bot_controller/controller.py
bot_controller/hdlc.py
bot_controller/joystick.py
bot_controller/keyboard.py
bot_controller/main.py
bot_controller/models.py
bot_controller/protocol.py
bot_controller/serial_interface.py
bot_controller/server.py
bot_controller/frontend/.env
bot_controller/frontend/.gitignore
bot_controller/frontend/package-lock.json
bot_controller/frontend/package.json
bot_controller/frontend/build/asset-manifest.json
bot_controller/frontend/build/index.html
bot_controller/frontend/build/manifest.json
bot_controller/frontend/build/robots.txt
bot_controller/frontend/build/static/css/main.ab17a09a.css
bot_controller/frontend/build/static/css/main.ab17a09a.css.map
bot_controller/frontend/build/static/js/main.7c4dac36.js
bot_controller/frontend/build/static/js/main.7c4dac36.js.LICENSE.txt
bot_controller/frontend/build/static/js/main.7c4dac36.js.map
bot_controller/frontend/build/static/media/bootstrap-icons.e559bf06bc84fd9525e6.woff
bot_controller/frontend/build/static/media/bootstrap-icons.ea98e12d2d58747f9fc5.woff2
bot_controller/frontend/public/index.html
bot_controller/frontend/public/manifest.json
bot_controller/frontend/public/robots.txt
bot_controller/frontend/src/DotBots.js
bot_controller/frontend/src/index.js
bot_controller/tests/test_controller.py
bot_controller/tests/test_hdlc_handler.py
bot_controller/tests/test_main.py
bot_controller/tests/test_protocol.py
utils/hooks/webapp.py
dotbot_controller-0.5.1.dist-info/METADATA
dotbot_controller-0.5.1.dist-info/WHEEL
dotbot_controller-0.5.1.dist-info/entry_points.txt
dotbot_controller-0.5.1.dist-info/licenses/LICENSE.txt
dotbot_controller-0.5.1.dist-info/RECORD
